gitmopy/__init__.py
gitmopy/cli.py
gitmopy/constants.py
gitmopy/git.py
gitmopy/history.py
gitmopy/prompt.py
gitmopy/utils.py
gitmopy/assets/ai_devmojis.yaml
gitmopy/assets/conventional.yaml
gitmopy/assets/gitmojis.yaml
gitmopy-0.6.0.dist-info/METADATA
gitmopy-0.6.0.dist-info/WHEEL
gitmopy-0.6.0.dist-info/entry_points.txt
gitmopy-0.6.0.dist-info/licenses/LICENSE
gitmopy-0.6.0.dist-info/RECORD
