Metadata-Version: 2.4
Name: gitmopy
Version: 0.6.0
Summary: A python command-line for gitmoji
Project-URL: Homepage, https://github.com/vict0rsch/gitmopy
Project-URL: Repository, https://github.com/vict0rsch/gitmopy
Project-URL: Documentation, https://gitmopy.rtfd.io
Author-email: vict0rsch <vsch@pm.me>
License: MIT
License-File: LICENSE
Requires-Python: >=3.9
Requires-Dist: emoji>=2.14.1
Requires-Dist: gitpython>=3.1.31
Requires-Dist: inquirerpy>=0.3.4
Requires-Dist: pyyaml>=6.0
Requires-Dist: typer[all]>=0.8.0
Requires-Dist: wcwidth>=0.2.13
Provides-Extra: dev
Requires-Dist: black>=23.3.0; extra == 'dev'
Requires-Dist: ipython>=8.14.0; extra == 'dev'
Requires-Dist: isort>=5.12.0; extra == 'dev'
Requires-Dist: pydocstyle>=6.3.0; extra == 'dev'
